Workbook

Sheet Cover
A1: AVSAR - Startup-Friendly Public Procurement Platform
A2: Risk Register
A4: Document ID | B4: AVSAR-RSK-007
A5: Version | B5: 1.0
A6: Date | B6: 03 September 2026
A7: Prepared by | B7: TandSol
A8: Status | B8: Living
A9: Related documents | B9: AVSAR-HBK-001, AVSAR-CHR-002, AVSAR-PMP-003, AVSAR-RTM-004, AVSAR-SDD-005, AVSAR-CDR-006, AVSAR-TML-008, AVSAR-DPD-009, AVSAR-RET-010, AVSAR-QAB-011
A10: Classification | B10: Internal - Smart India Hackathon submission
A12: Purpose | B12: Risks to the AVSAR mechanism and to its delivery, scored on likelihood and impact. Score and Severity are formulas, not typed values, so re-scoring a risk reclassifies it automatically. Each mitigation states the specific control that addresses the risk, not an intention.
A14: Revision history
A15: Version | B15: Date | C15: Author | D15: Change
A16: 1.0 | B16: 03 Sep 2026 | C16: TandSol | D16: Baseline. Sixteen risks across adoption, legal, compliance, financial, integrity, security, technical and operational categories.
A19: Scoring | B19: Score = Likelihood x Impact. High >= 15, Medium 8-14, Low 1-7. Both columns are formulas; see the Scoring Key tab.

Sheet Legend
A1: Category
A2: Adoption | B2: Whether departments and startups actually use the mechanism
A3: Legal | B3: Challenge to an award, or to the process that produced it
A4: Compliance | B4: Statutory or regulatory obligation
A5: Financial | B5: Public money at risk, or supplier cash flow
A6: Integrity | B6: Fairness and defensibility of a decision
A7: Security | B7: Confidentiality, integrity or availability of the platform
A8: Technical | B8: Engineering or scaling risk
A9: Operational | B9: Capacity, process and coordination
A11: Response strategy
A12: Avoid | B12: Change the approach so the risk cannot arise
A13: Mitigate | B13: Reduce likelihood or impact with a named control
A14: Transfer | B14: Move the exposure to a party better placed to carry it
A15: Accept | B15: Consciously carry it, with the reasoning recorded
A17: Status
A18: Open | B18: Live, being managed
A19: Mitigated | B19: Control in place and evidenced; residual score recorded
A20: Closed | B20: No longer applicable; reason recorded
A21: Realised | B21: The risk occurred; managed as an issue
A23: Severity bands
A24: High | B24: Score 15 to 25. Named owner, mitigation with a target date, reviewed weekly.
A25: Medium | B25: Score 8 to 14. Mitigation planned, reviewed fortnightly.
A26: Low | B26: Score 1 to 7. Monitored, reviewed at each phase gate.

Sheet Risk Register
A1: Risk ID | B1: Category | C1: Description | D1: Cause / Trigger | E1: Impact | F1: Likelihood (1-5) | G1: Impact (1-5) | H1: Score | I1: Severity | J1: Response | K1: Mitigation | L1: Owner | M1: Status | N1: Target Date
A2: R-01 | B2: Adoption | C2: Departments do not publish problem statements because writing an outcome is harder than copying a specification. | D2: No in-house practice of outcome-based specification; no worked examples to copy. | E2: The platform has no supply of problems and the whole mechanism stalls at stage one. | F2: 4 | G2: 5 | H2: =F2*G2 | I2: =IF(H2>=15,"High",IF(H2>=8,"Medium","Low")) | J2: Mitigate | K2: The authoring form makes baseline, KPI, unit and direction separate mandatory fields and refuses to publish without a measurable KPI. Ship a library of published problem statements as worked examples, and a one-page authoring guide in the reference section. | L2: Mission Director | M2: Open | N2: 31 Oct 2026
A3: R-02 | B3: Legal | C3: A single-source award after a pilot is challenged as favouritism. | D3: Single-source procurement is inherently contestable where the pilot participant is also the awardee. | E3: Award set aside; a chilling effect on every other department considering the route. | F3: 3 | G3: 5 | H3: =F3*G3 | I3: =IF(H3>=15,"High",IF(H3>=8,"Medium","Low")) | J3: Mitigate | K3: Four controls in combination: the problem statement is public before anyone applies; eligibility is decided by statute not opinion; scoring is blind against a rubric published in advance with a mandatory conflict-of-interest declaration and a locked score; and every procurement carries a written justification and a named GFR provision on its face. Where more than one pilot clears the gate the mode is a limited tender among participants under Rule 162, not single source. | L3: Director (Procurement) | M3: Open | N3: Continuous
A4: R-03 | B4: Compliance | C4: Personal data handled during a pilot is processed beyond the declared purpose. | D4: A startup gains access to citizen data in a live environment for a limited operational purpose. | E4: DPDP Act 2023 breach, penalty exposure, and reputational damage to the mechanism itself. | F4: 3 | G4: 5 | H4: =F4*G4 | I4: =IF(H4>=15,"High",IF(H4>=8,"Medium","Low")) | J4: Mitigate | K4: Pilot activation is blocked by the platform until the data processing agreement is recorded (HTTP 412, asserted in the end-to-end suite). Purpose is bounded by the pilot scope; the retention policy sets an erasure trigger per data category; the audit trail records every access-granting transition. | L4: Nodal Officer | M4: Open | N4: Continuous
A5: R-04 | B5: Financial | C5: A pilot consumes budget and produces no usable outcome. | D5: Genuine technical uncertainty, which is the reason a pilot exists. | E5: Sunk cost and, more damaging, a department that concludes the whole model does not work. | F5: 4 | G5: 3 | H5: =F5*G5 | I5: =IF(H5>=15,"High",IF(H5>=8,"Medium","Low")) | J5: Accept | K5: Accepted by design and priced in: the pilot budget is capped and ring-fenced, payment is released only against accepted milestone evidence, and the agreement carries an exit clause. A failed pilot is published on the transparency board rather than hidden, so the base rate is visible and a single failure is not read as a verdict on the mechanism. | L5: Department Head | M5: Open | N5: Continuous
A6: R-05 | B6: Integrity | C6: An evaluator scores an applicant with whom they have an undeclared interest. | D6: Small expert pools in specialised sectors mean genuine overlap is common. | E6: A tainted shortlist that cannot be defended, and a grievance that succeeds. | F6: 3 | G6: 4 | H6: =F6*G6 | I6: =IF(H6>=15,"High",IF(H6>=8,"Medium","Low")) | J6: Mitigate | K6: A conflict-of-interest declaration is a precondition the API enforces before any score is accepted. The first pass is blind. Scores lock on submission. Committee dispersion above twenty marks forces a reconciliation sitting. Every submission is written to the hash-chained audit trail with the evaluator identified. | L6: Nodal Officer | M6: Open | N6: Continuous
A7: R-06 | B7: Financial | C7: Payment to a startup breaches the statutory forty-five-day window. | D7: Treasury and PFMS processing queues sit outside the platform's control. | E7: Interest liability under the MSMED Act, and cash-flow failure at a supplier for whom this is existential. | F7: 4 | G7: 4 | H7: =F7*G7 | I7: =IF(H7>=15,"High",IF(H7>=8,"Medium","Low")) | J7: Mitigate | K7: The clock starts automatically on milestone acceptance and is visible to both parties. Breaches are counted on the public transparency board. The startup has a named grievance category with a fifteen-day SLA that escalates to the department head. | L7: Director (Procurement) | M7: Open | N7: Continuous
A8: R-07 | B8: Technical | C8: A solution proven at pilot scale fails at production scale. | D8: A pilot is deliberately small; some failure modes appear only at volume. | E8: A live public service degrades, and the rate contract has already been extended to other departments. | F8: 3 | G8: 4 | H8: =F8*G8 | I8: =IF(H8>=15,"High",IF(H8>=8,"Medium","Low")) | J8: Mitigate | K8: Scalability and interoperability is a scored technical criterion. The problem statement declares the indicative scale-up volume up front so the applicant designs for it. Rate contracts run two years with an exit, and the registry records adoption counts so a systemic problem surfaces early. | L8: Chief Engineer | M8: Open | N8: Continuous
A9: R-08 | B9: Adoption | C9: Startups do not apply because the pilot value does not justify the effort. | D9: A capped pilot is small relative to the cost of selling into government. | E9: Thin applicant pools; the department concludes the market cannot deliver. | F9: 3 | G9: 4 | H9: =F9*G9 | I9: =IF(H9>=15,"High",IF(H9>=8,"Medium","Low")) | J9: Mitigate | K9: Every problem statement must declare the indicative scale-up value and volume, which is what makes a small pilot worth the effort. EMD and tender fee are exempt, so applying costs only the work. The Proven Solutions Registry means one cleared pilot can generate orders from several departments. | L9: Mission Director | M9: Open | N9: 31 Dec 2026
A10: R-09 | B10: Security | C10: The audit log is altered to conceal an irregular award. | D10: Privileged database access exists in any real deployment. | E10: Loss of the evidentiary basis for every decision on the platform; audit findings against the department. | F10: 2 | G10: 5 | H10: =F10*G10 | I10: =IF(H10>=15,"High",IF(H10>=8,"Medium","Low")) | J10: Mitigate | K10: The log is append-only and hash-chained: each entry hashes its predecessor, so any retrospective edit invalidates every subsequent link. A full-chain verification is exposed to the administrator and to audit, and the end-to-end suite asserts integrity after a complete lifecycle run. | L10: Scientist-E (NIC) | M10: Open | N10: Continuous
A11: R-10 | B11: Technical | C11: Startup identity claims are accepted without verification. | D11: The demonstration build stubs MCA, GSTN and Udyam verification. | E11: An ineligible entity clears the gate; every downstream decision is unsound. | F11: 4 | G11: 4 | H11: =F11*G11 | I11: =IF(H11>=15,"High",IF(H11>=8,"Medium","Low")) | J11: Mitigate | K11: The gate already records the declaration, the verdict and the rule, so a false claim is attributable. Live API verification against MCA (CIN), GSTN (GSTIN) and the Udyam registry is the first item on the deployment roadmap and is a hard precondition for any live award. | L11: Scientist-E (NIC) | M11: Open | N11: 30 Nov 2026
A12: R-11 | B12: Compliance | C12: The interface fails a GIGW 3.0 or WCAG 2.1 AA conformance audit. | D12: Conformance was designed for but not independently tested. | E12: Cannot be deployed on a government domain; rework late in the programme. | F12: 3 | G12: 3 | H12: =F12*G12 | I12: =IF(H12>=15,"High",IF(H12>=8,"Medium","Low")) | J12: Mitigate | K12: Built to the standard from the outset: semantic landmarks, skip link, focus never suppressed, no meaning carried by colour alone, reduced-motion honoured. A third-party conformance audit is scheduled before deployment and is recorded as a gate, not an aspiration. | L12: Scientist-E (NIC) | M12: Open | N12: 31 Jan 2027
A13: R-12 | B13: Operational | C13: Departments duplicate effort by publishing problem statements another department has already solved. | D13: No habit of checking what has already been proven elsewhere. | E13: The central benefit of the mechanism is lost and public money buys the same lesson twice. | F13: 3 | G13: 3 | H13: =F13*G13 | I13: =IF(H13>=15,"High",IF(H13>=8,"Medium","Low")) | J13: Mitigate | K13: The Proven Solutions Registry is a first-class navigation item on the public site and in every departmental workspace, and it carries the measured pilot KPIs so a second department sees evidence rather than a claim. Adoption is one click and skips discovery, evaluation and pilot. | L13: Mission Director | M13: Open | N13: Continuous
... A17: R-16 | B17: Technical | C17: The platform cannot integrate with GeM, PFMS or CPPP within the programme timeline. | D17: Onboarding to central systems is a governance process, not an engineering task. | E17: Manual re-entry of orders and payment status; the single-file-number claim weakens. | F17: 3 | G17: 3 | H17: =F17*G17 | I17: =IF(H17>=15,"High",IF(H17>=8,"Medium","Low")) | J17: Transfer | K17: Integration points are already isolated behind named fields (GeM contract id, PFMS reference, purchase order number) so a live adapter replaces a stub without schema change. Onboarding is initiated in parallel with development and tracked as a dependency owned outside the engineering team. | L17: Mission Director | M17: Open | N17: 28 Feb 2027

Sheet Scoring Key
A1: Risk scoring key
A3: Score = Likelihood x Impact
A4: High >= 15 (red) Medium 8-14 (amber) Low 1-7 (green)
A6: Likelihood
A7: 1 | B7: Rare - no comparable occurrence in similar programmes
A8: 2 | B8: Unlikely - has occurred elsewhere but conditions differ
A9: 3 | B9: Possible - has occurred in comparable programmes
A10: 4 | B10: Likely - expected unless actively managed
A11: 5 | B11: Almost certain - will occur without a control
A13: Impact
A14: 1 | B14: Negligible - absorbed without schedule or cost effect
A15: 2 | B15: Minor - local rework, no external effect
A16: 3 | B16: Moderate - schedule slip or a visible degradation of the mechanism
A17: 4 | B17: Major - a stage of the mechanism stops working as intended
A18: 5 | B18: Severe - award set aside, statutory breach, or loss of confidence in the model
A21: Matrix (Likelihood down, Impact across)
B22: 1 | C22: 2 | D22: 3 | E22: 4 | F22: 5
A23: 1 | B23: 1 | C23: 2 | D23: 3 | E23: 4 | F23: 5
A24: 2 | B24: 2 | C24: 4 | D24: 6 | E24: 8 | F24: 10
A25: 3 | B25: 3 | C25: 6 | D25: 9 | E25: 12 | F25: 15
A26: 4 | B26: 4 | C26: 8 | D26: 12 | E26: 16 | F26: 20
A27: 5 | B27: 5 | C27: 10 | D27: 15 | E27: 20 | F27: 25

Sheet Summary
A1: Risk register - summary
A3: Risks registered | B3: =COUNTA('Risk Register'!A2:A17) | C3: Total rows
A4: High severity | B4: =COUNTIF('Risk Register'!I2:I17,"High") | C4: Score 15 or above; weekly review
A5: Medium severity | B5: =COUNTIF('Risk Register'!I2:I17,"Medium") | C5: Score 8 to 14; fortnightly review
A6: Low severity | B6: =COUNTIF('Risk Register'!I2:I17,"Low") | C6: Score 1 to 7; reviewed at phase gates
A7: Highest score on the register | B7: =MAX('Risk Register'!H2:H17) | C7: Drives the escalation cadence
A8: Mean score | B8: =ROUND(AVERAGE('Risk Register'!H2:H17),1) | C8: Overall exposure indicator
A9: Open | B9: =COUNTIF('Risk Register'!M2:M17,"Open") | C9: Live and being managed
A10: Mitigated | B10: =COUNTIF('Risk Register'!M2:M17,"Mitigated") | C10: Control in place and evidenced
A11: Accepted | B11: =COUNTIF('Risk Register'!J2:J17,"Accept") | C11: Consciously carried, reasoning recorded
A12: Transferred | B12: =COUNTIF('Risk Register'!J2:J17,"Transfer") | C12: Carried by another party
A13: Compliance-category risks | B13: =COUNTIF('Risk Register'!B2:B17,"Compliance") | C13: Cross-check against AVSAR-DPD-009
A14: Risks with no target date | B14: =COUNTIF('Risk Register'!N2:N17,"") | C14: Must be zero
A16: Score and Severity on the register are formulas. Change a Likelihood or Impact cell and every figure here updates; nothing on this tab is typed.
